{
    "api_base_url": "https://api.awnr.site",
    "tg_bot": "vpn_naruzhu_support_bot",
    "tg_key_bot": "vpn_naruzhu_support_bot",
    "vpn_connections": [
        {
            "country_code": "*",
            "title": "Умный режим",
            "title_localized": {
              "ru": "Умный режим",
              "en": "Smart"
            },
            "configuration_url": null,
            "vpn_type": "wg",
            "is_api_basic_auth_enabled": false,
            "relative_path": "client-api/v1/download-awg-key?key_type=smart",
            "anonymous_relative_path": "client-api/v1/download-anonymous-key?key_type=smart",
            "key_type": "smart"
        },
        {
            "country_code": "*",
            "title": "Напрямую",
            "title_localized": {
              "ru": "Напрямую",
              "en": "Direct"
            },
            "configuration_url": null,
            "vpn_type": "wg",
            "is_api_basic_auth_enabled": false,
            "relative_path": "client-api/v1/download-awg-key?key_type=direct",
            "anonymous_relative_path": "client-api/v1/download-anonymous-key?key_type=direct",
            "key_type": "direct"
        }
    ],
    "privacy_policy_url": "https://telegra.ph/Privacy-Policy-06-01-98",
    "tos_url": "http://www.apple.com/legal/itunes/appstore/dev/stdeula",
    "quick_login_url": "nrz.monster/quick-login",
    "paywall_main_product_id": "premium_monthly",
    "paywall_monthly_product_id": "premium_monthly",
    "paywall_yearly_product_id": "premium_annual",
    "web_product_price": 490,
    "is_hybrid_paywall_enabled": true,
    "is_client_api_enabled": false,
    "hybrid_storefront_country_codes": ["*"],
    "hybrid_storefront_geo_ip_country_codes": ["*"],
    "is_country_selector_enabled": true,
    "is_change_server_enabled": true
}
